Workbook

Sheet DASHBOARD
B2: AI CONSTRUCTION INTELLIGENCE PLATFORM | EVM Dashboard
B5: Portfólio Consolidado · Earned Value Management · 16/05/2026
B7: CPI MÉDIO | D7: SPI MÉDIO | F7: EAC TOTAL | H7: VAC TOTAL | J7: TCPI MÉDIO | L7: % EXEC MÉD
B8: =PORTFOLIO!C9 -> 0.86355171 | D8: =PORTFOLIO!D9 -> 0.95008249 | F8: =PORTFOLIO!H9 -> 93815189 | H8: =PORTFOLIO!J9 -> -16115189 | J8: =PORTFOLIO!K9 -> 1.1125605 | L8: =PORTFOLIO!B9 -> 0.49333333
B10: OBRA | C10: % EXEC | D10: CPI | E10: SPI | F10: BAC | G10: PV | H10: EV | I10: EAC | J10: AC | K10: VAC | L10: TCPI | M10: STATUS
B11: Edifício Horizonte — Torre A | C11: =PORTFOLIO!B5 -> 0.72 | D11: =PORTFOLIO!C5 -> 1.0289483 | E11: =PORTFOLIO!D5 -> 1.0495627 | F11: =PORTFOLIO!E5 -> 23400000 | G11: =PORTFOLIO!F5 -> 16052400 | H11: =PORTFOLIO!G5 -> 16848000 | I11: =PORTFOLIO!H5 -> 22741667 | J11: =PORTFOLIO!I5 -> 16374000 | ... M11: =PORTFOLIO!L5 -> ✔ OK
B12: Condomínio Vale Verde | C12: =PORTFOLIO!B6 -> 0.45 | D12: =PORTFOLIO!C6 -> 0.81887662 | E12: =PORTFOLIO!D6 -> 0.81967213 | F12: =PORTFOLIO!E6 -> 16200000 | G12: =PORTFOLIO!F6 -> 8893800 | H12: =PORTFOLIO!G6 -> 7290000 | I12: =PORTFOLIO!H6 -> 19783200 | J12: =PORTFOLIO!I6 -> 8902440 | ... M12: =PORTFOLIO!L6 -> ⚠ ALERTA
B13: Complexo Industrial Norte | C13: =PORTFOLIO!B7 -> 0.31 | D13: =PORTFOLIO!C7 -> 0.74283019 | E13: =PORTFOLIO!D7 -> 0.98101266 | F13: =PORTFOLIO!E7 -> 38100000 | G13: =PORTFOLIO!F7 -> 12039600 | H13: =PORTFOLIO!G7 -> 11811000 | I13: =PORTFOLIO!H7 -> 51290323 | J13: =PORTFOLIO!I7 -> 15900000 | ... M13: =PORTFOLIO!L7 -> ✖ CRÍTICO

Sheet PORTFOLIO
A1: PORTFÓLIO CONSOLIDADO — EVM
A2: Valores em R$. Indicadores adimensionais. Atualizado: 16/05/2026
A4: OBRA | B4: % EXEC | C4: CPI | D4: SPI | E4: BAC (R$) | F4: PV (R$) | G4: EV (R$) | H4: EAC (R$) | I4: AC (R$) | J4: VAC (R$) | K4: TCPI | L4: STATUS
A5: Edifício Horizonte — Torre A | B5: =HORIZONTE!B6 -> 0.72 | C5: =IF(HORIZONTE!B13=0,0,HORIZONTE!B12/HORIZONTE!B13) -> 1.0289483 | D5: =IF(HORIZONTE!B11=0,0,HORIZONTE!B12/HORIZONTE!B11) -> 1.0495627 | E5: =HORIZONTE!B4 -> 23400000 | F5: =HORIZONTE!B11 -> 16052400 | G5: =HORIZONTE!B12 -> 16848000 | H5: =IF(HORIZONTE!B16=0,HORIZONTE!B4,HORIZONTE!B4/HORIZONTE!B16) -> 22741667 | I5: =HORIZONTE!B13 -> 16374000 | J5: =HORIZONTE!B4-IF(HORIZONTE!B16=0,HORIZONTE!B4,HORIZONTE!B4/HORIZONTE!B16) -> 658333.33 | K5: =IF((HORIZONTE!B4-HORIZONTE!B13)=0,0,(HORIZONTE!B4-HORIZONTE!B12)/(HORIZONTE!B4-HORIZONTE!B13)) -> 0.93253629 | L5: =IF(C5>=0.95,"✔ OK",IF(C5>=0.8,"⚠ ALERTA","✖ CRÍTICO")) -> ✔ OK
A6: Condomínio Vale Verde | B6: =VALE_VERDE!B6 -> 0.45 | C6: =IF(VALE_VERDE!B13=0,0,VALE_VERDE!B12/VALE_VERDE!B13) -> 0.81887662 | D6: =IF(VALE_VERDE!B11=0,0,VALE_VERDE!B12/VALE_VERDE!B11) -> 0.81967213 | E6: =VALE_VERDE!B4 -> 16200000 | F6: =VALE_VERDE!B11 -> 8893800 | G6: =VALE_VERDE!B12 -> 7290000 | H6: =IF(VALE_VERDE!B16=0,VALE_VERDE!B4,VALE_VERDE!B4/VALE_VERDE!B16) -> 19783200 | I6: =VALE_VERDE!B13 -> 8902440 | J6: =VALE_VERDE!B4-IF(VALE_VERDE!B16=0,VALE_VERDE!B4,VALE_VERDE!B4/VALE_VERDE!B16) -> -3583200 | K6: =IF((VALE_VERDE!B4-VALE_VERDE!B13)=0,0,(VALE_VERDE!B4-VALE_VERDE!B12)/(VALE_VERDE!B4-VALE_VERDE!B13)) -> 1.220956 | L6: =IF(C6>=0.95,"✔ OK",IF(C6>=0.8,"⚠ ALERTA","✖ CRÍTICO")) -> ⚠ ALERTA
A7: Complexo Industrial Norte | B7: =INDUSTRIAL!B6 -> 0.31 | C7: =IF(INDUSTRIAL!B13=0,0,INDUSTRIAL!B12/INDUSTRIAL!B13) -> 0.74283019 | D7: =IF(INDUSTRIAL!B11=0,0,INDUSTRIAL!B12/INDUSTRIAL!B11) -> 0.98101266 | E7: =INDUSTRIAL!B4 -> 38100000 | F7: =INDUSTRIAL!B11 -> 12039600 | G7: =INDUSTRIAL!B12 -> 11811000 | H7: =IF(INDUSTRIAL!B16=0,INDUSTRIAL!B4,INDUSTRIAL!B4/INDUSTRIAL!B16) -> 51290323 | I7: =INDUSTRIAL!B13 -> 15900000 | J7: =INDUSTRIAL!B4-IF(INDUSTRIAL!B16=0,INDUSTRIAL!B4,INDUSTRIAL!B4/INDUSTRIAL!B16) -> -13190323 | K7: =IF((INDUSTRIAL!B4-INDUSTRIAL!B13)=0,0,(INDUSTRIAL!B4-INDUSTRIAL!B12)/(INDUSTRIAL!B4-INDUSTRIAL!B13)) -> 1.1841892 | L7: =IF(C7>=0.95,"✔ OK",IF(C7>=0.8,"⚠ ALERTA","✖ CRÍTICO")) -> ✖ CRÍTICO
A9: PORTFÓLIO CONSOLIDADO (média/soma) | B9: =AVERAGE(B5:B7) -> 0.49333333 | C9: =AVERAGE(C5:C7) -> 0.86355171 | D9: =AVERAGE(D5:D7) -> 0.95008249 | E9: =SUM(E5:E7) -> 77700000 | F9: =SUM(F5:F7) -> 36985800 | G9: =SUM(G5:G7) -> 35949000 | H9: =SUM(H5:H7) -> 93815189 | I9: =SUM(I5:I7) -> 41176440 | J9: =SUM(J5:J7) -> -16115189 | K9: =AVERAGE(K5:K7) -> 1.1125605 | L9: —

Sheet Sheet

Sheet VALE_VERDE
A1: EVM — Condomínio Vale Verde
A2: AI Construction Intelligence Platform v5.2 · Cost_Controller_AI
A3: PREMISSAS (células em azul — altere conforme o projeto)
A4: Orçamento Total — BAC | B4: 16200000 | C4: INPUT | D4: Budget at Completion
A5: % do Escopo Planejado (PV%) | B5: 0.549 | C5: INPUT | D5: Percentual planejado acumulado
A6: % do Escopo Realizado (EV%) | B6: 0.45 | C6: INPUT | D6: Percentual fisicamente concluído
A7: Custo Real Incorrido (AC) | B7: 8902440 | C7: INPUT | D7: Actual Cost — total gasto até hoje
A8: Prazo Planejado (meses) | B8: 30 | C8: INPUT | D8: Duração planejada total
A9: Prazo Real Decorrido (meses) | B9: 16 | C9: INPUT | D9: Meses efetivamente decorridos
A10: INDICADORES EVM (calculados automaticamente — não edite)
A11: PV — Planned Value (BCWS) | B11: =B4*B5 -> 8893800 | C11: CALC | D11: Valor planejado acumulado = BAC × PV%
A12: EV — Earned Value (BCWP) | B12: =B4*B6 -> 7290000 | C12: CALC | D12: Valor agregado = BAC × EV%
A13: AC — Actual Cost (ACWP) | B13: =B7 -> 8902440 | C13: CALC | D13: Custo real incorrido (igual à premissa)
A14: CV — Cost Variance | B14: =B12-B13 -> -1612440 | C14: CALC | D14: EV - AC | Negativo = estouro de custo
A15: SV — Schedule Variance | B15: =B12-B11 -> -1603800 | C15: CALC | D15: EV - PV | Negativo = atraso
A16: CPI — Cost Performance Index | B16: =IF(B13=0,0,B12/B13) -> 0.81887662 | C16: CALC | D16: > 1.00 abaixo do orçamento | < 1.00 estouro
A17: SPI — Sched. Performance Idx | B17: =IF(B11=0,0,B12/B11) -> 0.81967213 | C17: CALC | D17: > 1.00 adiantado | < 1.00 atrasado
A18: EAC — Estimate at Completion | B18: =IF(B16=0,B4,B4/B16) -> 19783200 | C18: CALC | D18: BAC / CPI — custo total projetado
A19: TCPI— To-Complete Perf. Idx | B19: =IF((B4-B13)=0,0,(B4-B12)/(B4-B13)) -> 1.220956 | C19: CALC | D19: (BAC-EV)/(BAC-AC) | índice necessário para atingir BAC
A20: VAC — Variance at Completion | B20: =B4-B18 -> -3583200 | C20: CALC | D20: BAC - EAC | Negativo = projeção de estouro
A21: ETC — Estimate to Complete | B21: =B18-B13 -> 10880760 | C21: CALC | D21: EAC - AC | Quanto ainda falta gastar
A22: SPI(t) — Prazo | B22: =IF(B8=0,0,B9/B8) -> 0.53333333 | C22: CALC | D22: Índice de prazo no tempo
A23: SEMÁFORO DE DESEMPENHO
A24: Custo (CPI) | B24: =IF(B16>=0.95,"✔ DENTRO DO ORÇAMENTO",IF(B16>=0.8,"⚠ ALERTA DE CUSTO","✖ ESTOURO CRÍTICO")) -> ⚠ ALERTA DE CUSTO
A25: Prazo (SPI) | B25: =IF(B17>=0.95,"✔ DENTRO DO PRAZO",IF(B17>=0.8,"⚠ ATRASO MODERADO","✖ ATRASO CRÍTICO")) -> ⚠ ATRASO MODERADO
A26: Viabilidade (TCPI) | B26: =IF(B19<=1.1,"✔ META VIÁVEL",IF(B19<=1.2,"⚠ DESAFIADOR","✖ INVIÁVEL")) -> ✖ INVIÁVEL

Sheet HORIZONTE
A1: EVM — Edifício Horizonte — Torre A
A2: AI Construction Intelligence Platform v5.2 · Cost_Controller_AI
A3: PREMISSAS (células em azul — altere conforme o projeto)
A4: Orçamento Total — BAC | B4: 23400000 | C4: INPUT | D4: Budget at Completion
A5: % do Escopo Planejado (PV%) | B5: 0.686 | C5: INPUT | D5: Percentual planejado acumulado
A6: % do Escopo Realizado (EV%) | B6: 0.72 | C6: INPUT | D6: Percentual fisicamente concluído
A7: Custo Real Incorrido (AC) | B7: 16374000 | C7: INPUT | D7: Actual Cost — total gasto até hoje
A8: Prazo Planejado (meses) | B8: 24 | C8: INPUT | D8: Duração planejada total
A9: Prazo Real Decorrido (meses) | B9: 17 | C9: INPUT | D9: Meses efetivamente decorridos
A10: INDICADORES EVM (calculados automaticamente — não edite)
A11: PV — Planned Value (BCWS) | B11: =B4*B5 -> 16052400 | C11: CALC | D11: Valor planejado acumulado = BAC × PV%
A12: EV — Earned Value (BCWP) | B12: =B4*B6 -> 16848000 | C12: CALC | D12: Valor agregado = BAC × EV%
A13: AC — Actual Cost (ACWP) | B13: =B7 -> 16374000 | C13: CALC | D13: Custo real incorrido (igual à premissa)
A14: CV — Cost Variance | B14: =B12-B13 -> 474000 | C14: CALC | D14: EV - AC | Negativo = estouro de custo
A15: SV — Schedule Variance | B15: =B12-B11 -> 795600 | C15: CALC | D15: EV - PV | Negativo = atraso
A16: CPI — Cost Performance Index | B16: =IF(B13=0,0,B12/B13) -> 1.0289483 | C16: CALC | D16: > 1.00 abaixo do orçamento | < 1.00 estouro
A17: SPI — Sched. Performance Idx | B17: =IF(B11=0,0,B12/B11) -> 1.0495627 | C17: CALC | D17: > 1.00 adiantado | < 1.00 atrasado
A18: EAC — Estimate at Completion | B18: =IF(B16=0,B4,B4/B16) -> 22741667 | C18: CALC | D18: BAC / CPI — custo total projetado
A19: TCPI— To-Complete Perf. Idx | B19: =IF((B4-B13)=0,0,(B4-B12)/(B4-B13)) -> 0.93253629 | C19: CALC | D19: (BAC-EV)/(BAC-AC) | índice necessário para atingir BAC
A20: VAC — Variance at Completion | B20: =B4-B18 -> 658333.33 | C20: CALC | D20: BAC - EAC | Negativo = projeção de estouro
A21: ETC — Estimate to Complete | B21: =B18-B13 -> 6367666.7 | C21: CALC | D21: EAC - AC | Quanto ainda falta gastar
A22: SPI(t) — Prazo | B22: =IF(B8=0,0,B9/B8) -> 0.70833333 | C22: CALC | D22: Índice de prazo no tempo
A23: SEMÁFORO DE DESEMPENHO
A24: Custo (CPI) | B24: =IF(B16>=0.95,"✔ DENTRO DO ORÇAMENTO",IF(B16>=0.8,"⚠ ALERTA DE CUSTO","✖ ESTOURO CRÍTICO")) -> ✔ DENTRO DO ORÇAMENTO
A25: Prazo (SPI) | B25: =IF(B17>=0.95,"✔ DENTRO DO PRAZO",IF(B17>=0.8,"⚠ ATRASO MODERADO","✖ ATRASO CRÍTICO")) -> ✔ DENTRO DO PRAZO
A26: Viabilidade (TCPI) | B26: =IF(B19<=1.1,"✔ META VIÁVEL",IF(B19<=1.2,"⚠ DESAFIADOR","✖ INVIÁVEL")) -> ✔ META VIÁVEL

Sheet CURVA_S
A1: CURVA S — PORTFÓLIO CONSOLIDADO
A2: Valores acumulados em R$ M · Azul=Planejado · Verde=Realizado · Laranja=EAC Projetado
A4: MÊS | B4: PV ACUM (R$M) | C4: EV ACUM (R$M) | D4: AC ACUM (R$M) | E4: FORECAST (R$M)
A5: Jan/25 | B5: 8.2 | C5: 6.1 | D5: 6.4
A6: Fev/25 | B6: 18.4 | C6: 14.2 | D6: 14.9
A7: Mar/25 | B7: 31 | C7: 25.8 | D7: 26.7
A8: Abr/25 | B8: 47.2 | C8: 40.3 | D8: 41.8
A9: Mai/25 | B9: 65.4 | C9: 56.7 | D9: 58.6
A10: Jun/25 | B10: 81.6 | C10: 68.5 | D10: 70.9
A11: Jul/25 | E11: 88.2
A12: Ago/25 | E12: 98.7
A13: Set/25 | E13: 110.4
A14: Out/25 | E14: 121
A15: Nov/25 | E15: 133.2
A16: Dez/25 | E16: 146

Sheet INDUSTRIAL
A1: EVM — Complexo Industrial Norte
A2: AI Construction Intelligence Platform v5.2 · Cost_Controller_AI
A3: PREMISSAS (células em azul — altere conforme o projeto)
A4: Orçamento Total — BAC | B4: 38100000 | C4: INPUT | D4: Budget at Completion
A5: % do Escopo Planejado (PV%) | B5: 0.316 | C5: INPUT | D5: Percentual planejado acumulado
A6: % do Escopo Realizado (EV%) | B6: 0.31 | C6: INPUT | D6: Percentual fisicamente concluído
A7: Custo Real Incorrido (AC) | B7: 15900000 | C7: INPUT | D7: Actual Cost — total gasto até hoje
A8: Prazo Planejado (meses) | B8: 36 | C8: INPUT | D8: Duração planejada total
A9: Prazo Real Decorrido (meses) | B9: 12 | C9: INPUT | D9: Meses efetivamente decorridos
A10: INDICADORES EVM (calculados automaticamente — não edite)
A11: PV — Planned Value (BCWS) | B11: =B4*B5 -> 12039600 | C11: CALC | D11: Valor planejado acumulado = BAC × PV%
A12: EV — Earned Value (BCWP) | B12: =B4*B6 -> 11811000 | C12: CALC | D12: Valor agregado = BAC × EV%
A13: AC — Actual Cost (ACWP) | B13: =B7 -> 15900000 | C13: CALC | D13: Custo real incorrido (igual à premissa)
A14: CV — Cost Variance | B14: =B12-B13 -> -4089000 | C14: CALC | D14: EV - AC | Negativo = estouro de custo
A15: SV — Schedule Variance | B15: =B12-B11 -> -228600 | C15: CALC | D15: EV - PV | Negativo = atraso
A16: CPI — Cost Performance Index | B16: =IF(B13=0,0,B12/B13) -> 0.74283019 | C16: CALC | D16: > 1.00 abaixo do orçamento | < 1.00 estouro
A17: SPI — Sched. Performance Idx | B17: =IF(B11=0,0,B12/B11) -> 0.98101266 | C17: CALC | D17: > 1.00 adiantado | < 1.00 atrasado
A18: EAC — Estimate at Completion | B18: =IF(B16=0,B4,B4/B16) -> 51290323 | C18: CALC | D18: BAC / CPI — custo total projetado
A19: TCPI— To-Complete Perf. Idx | B19: =IF((B4-B13)=0,0,(B4-B12)/(B4-B13)) -> 1.1841892 | C19: CALC | D19: (BAC-EV)/(BAC-AC) | índice necessário para atingir BAC
A20: VAC — Variance at Completion | B20: =B4-B18 -> -13190323 | C20: CALC | D20: BAC - EAC | Negativo = projeção de estouro
A21: ETC — Estimate to Complete | B21: =B18-B13 -> 35390323 | C21: CALC | D21: EAC - AC | Quanto ainda falta gastar
A22: SPI(t) — Prazo | B22: =IF(B8=0,0,B9/B8) -> 0.33333333 | C22: CALC | D22: Índice de prazo no tempo
A23: SEMÁFORO DE DESEMPENHO
A24: Custo (CPI) | B24: =IF(B16>=0.95,"✔ DENTRO DO ORÇAMENTO",IF(B16>=0.8,"⚠ ALERTA DE CUSTO","✖ ESTOURO CRÍTICO")) -> ✖ ESTOURO CRÍTICO
A25: Prazo (SPI) | B25: =IF(B17>=0.95,"✔ DENTRO DO PRAZO",IF(B17>=0.8,"⚠ ATRASO MODERADO","✖ ATRASO CRÍTICO")) -> ✔ DENTRO DO PRAZO
A26: Viabilidade (TCPI) | B26: =IF(B19<=1.1,"✔ META VIÁVEL",IF(B19<=1.2,"⚠ DESAFIADOR","✖ INVIÁVEL")) -> ⚠ DESAFIADOR

Sheet GLOSSÁRIO
A1: GLOSSÁRIO EVM + GUIA DE USO
A3: INDICADOR | B3: FÓRMULA | C3: INTERPRETAÇÃO
A4: BAC — Budget at Completion | B4: Orçamento total | C4: Custo total planejado para concluir o projeto
A5: PV — Planned Value (BCWS) | B5: BAC × % planejado | C5: Quanto deveria ter sido gasto até hoje pelo plano
A6: EV — Earned Value (BCWP) | B6: BAC × % realizado | C6: Valor do trabalho efetivamente concluído
A7: AC — Actual Cost (ACWP) | B7: Custo real incorrido | C7: Total gasto até a data de referência
A8: CV — Cost Variance | B8: EV - AC | C8: Positivo = economia | Negativo = estouro
A9: SV — Schedule Variance | B9: EV - PV | C9: Positivo = adiantado | Negativo = atrasado
A10: CPI — Cost Perf. Index | B10: EV / AC | C10: > 1 = abaixo do orçamento | < 1 = estouro
A11: SPI — Sched. Perf. Index | B11: EV / PV | C11: > 1 = adiantado | < 1 = atrasado
A12: EAC — Estimate at Completion | B12: BAC / CPI | C12: Projeção do custo total ao final do projeto
A13: ETC — Estimate to Complete | B13: EAC - AC | C13: Quanto ainda falta gastar para concluir
A14: VAC — Variance at Completion | B14: BAC - EAC | C14: Negativo = projeto vai estourar o orçamento
A15: TCPI — To-Complete Perf. | B15: (BAC-EV)/(BAC-AC) | C15: Índice de desempenho necessário para atingir BAC
A17: CONVENÇÃO DE CORES
A18: Texto AZUL | B18: Entrada manual (INPUT) | C18: Célula editável pelo usuário — altere conforme necessário
A19: Texto PRETO | B19: Fórmula calculada (CALC) | C19: Calculado automaticamente — NÃO edite
A20: Texto VERDE | B20: Link inter-abas | C20: Valor puxado de outra aba da planilha
A22: AGENTE IA INTEGRADO
A23: Cost_Controller_AI | B23: Reward signal | C23: 1 - |custo_real - EAC| / EAC (quanto mais próximo de 1, melhor)
A24: Frequência de update | B24: Mensal | C24: Atualizar B6 (% real) e B7 (AC) todo mês em cada aba de obra
A25: Meta CPI | B25: ≥ 0.95 | C25: Abaixo = alerta automático; < 0.80 = crítico
A26: Meta SPI | B26: ≥ 0.95 | C26: Abaixo = alerta de prazo
A27: TCPI viável | B27: ≤ 1.10 | C27: Acima = desafiador; > 1.20 = matematicamente inviável
